scine_swoose/__init__.py
scine_swoose/scine_swoose.so
scine_swoose/swoose.module.so
scine_swoose.libs/libboost_atomic-00e6ede8.so.1.78.0
scine_swoose.libs/libboost_filesystem-e9e1d9ac.so.1.78.0
scine_swoose.libs/libboost_system-c0fa27da.so.1.78.0
scine_swoose.libs/libcore-6a155538.so
scine_swoose.libs/libgomp-e985bcbb.so.1.0.0
scine_swoose.libs/libmolassembler-ca621eca.so
scine_swoose.libs/libpugixml-f1f42458.so.1.14
scine_swoose.libs/libutilsos-1a1c26a4.so
scine_swoose.libs/swoose-8e5de8e0.module.so
scine_swoose-3.0.0.dist-info/METADATA
scine_swoose-3.0.0.dist-info/WHEEL
scine_swoose-3.0.0.dist-info/top_level.txt
scine_swoose-3.0.0.dist-info/RECORD
